yieldbreaker/.__init__.py.un~
yieldbreaker/__init__.py
yieldbreaker-0.0.1.dist-info/WHEEL
yieldbreaker-0.0.1.dist-info/METADATA
yieldbreaker-0.0.1.dist-info/RECORD
